cellpose_counter/__init__.py
cellpose_counter/_version.py
cellpose_counter/_widget.py
cellpose_counter/counter.py
cellpose_counter/napari.yaml
cellpose_counter/_tests/__init__.py
cellpose_counter/_tests/test_counter.py
cellpose_counter/_tests/data/image_large_1024.tif
cellpose_counter/_tests/data/image_small_512.tif
cellpose_counter-0.1.8.dist-info/LICENSE
cellpose_counter-0.1.8.dist-info/METADATA
cellpose_counter-0.1.8.dist-info/WHEEL
cellpose_counter-0.1.8.dist-info/entry_points.txt
cellpose_counter-0.1.8.dist-info/top_level.txt
cellpose_counter-0.1.8.dist-info/RECORD
